f32nodes/__init__.py
f32nodes/core.py
f32nodes/gui.py
f32nodes/runner.py
f32nodes-0.1.1.dist-info/METADATA
f32nodes-0.1.1.dist-info/WHEEL
f32nodes-0.1.1.dist-info/licenses/LICENSE
f32nodes-0.1.1.dist-info/RECORD
