Metadata-Version: 2.4
Name: f32nodes
Version: 0.1.1
Summary: Float32-focused node graph runtime with PyQt visualizer and real-time instrumentation.
License: Apache-2.0
License-File: LICENSE
Author: Jan Nouruzi-Pur
Requires-Python: >=3.12
Classifier: License :: OSI Approved :: Apache Software License
Classifier: Programming Language :: Python :: 3
Classifier: Programming Language :: Python :: 3.12
Classifier: Programming Language :: Python :: 3.13
Classifier: Programming Language :: Python :: 3.14
Requires-Dist: PyQt6 (>=6.6,<7.0)
Requires-Dist: numpy (>=1.26,<2.0)
Requires-Dist: opencv-python (>=4.8.1.78,<5.0)
Requires-Dist: pyyaml (>=6.0.1,<7.0)
